pydictsql/__init__.py
pydictsql/dictfilter.py
pydictsql/exceptions.py
pydictsql/parser.py
pydictsql/tokeniser.py
pydictsql-0.1.0.dist-info/LICENSE.txt
pydictsql-0.1.0.dist-info/METADATA
pydictsql-0.1.0.dist-info/WHEEL
pydictsql-0.1.0.dist-info/RECORD
