Metadata-Version: 2.1
Name: pydictsql
Version: 0.1.0
Summary: 
Author: Martyn Pearson
Author-email: martynjpearson@hotmail.com
Requires-Python: >=3.12,<4.0
Classifier: Programming Language :: Python :: 3
Classifier: Programming Language :: Python :: 3.12
Classifier: Programming Language :: Python :: 3.13
